nemo_asr/__init__.py
nemo_asr/audio_preprocessing.py
nemo_asr/beam_search_decoder.py
nemo_asr/data_layer.py
nemo_asr/greedy_ctc_decoder.py
nemo_asr/helpers.py
nemo_asr/jasper.py
nemo_asr/losses.py
nemo_asr/metrics.py
nemo_asr/las/__init__.py
nemo_asr/las/helpers.py
nemo_asr/las/misc.py
nemo_asr/parts/__init__.py
nemo_asr/parts/cleaners.py
nemo_asr/parts/dataset.py
nemo_asr/parts/features.py
nemo_asr/parts/jasper.py
nemo_asr/parts/manifest.py
nemo_asr/parts/perturb.py
nemo_asr/parts/segment.py
nemo_asr/parts/spectr_augment.py
nemo_asr-0.9.0.dist-info/LICENSE
nemo_asr-0.9.0.dist-info/METADATA
nemo_asr-0.9.0.dist-info/WHEEL
nemo_asr-0.9.0.dist-info/top_level.txt
nemo_asr-0.9.0.dist-info/RECORD
