Metadata-Version: 2.1
Name: nemo-asr
Version: 0.9.0
Summary: Collection of Neural Modules for Speech Recognition
Home-page: https://github.com/nvidia/nemo
Author: NVIDIA
Author-email: nemo-toolkit@nvidia.com
License: UNKNOWN
Platform: UNKNOWN
Classifier: Programming Language :: Python :: 3
Classifier: Operating System :: OS Independent
Classifier: License :: OSI Approved :: Apache Software License
Requires-Dist: nemo-toolkit
Requires-Dist: librosa
Requires-Dist: num2words
Requires-Dist: inflect
Requires-Dist: kaldi-io
Requires-Dist: torch-stft
Requires-Dist: soundfile
Requires-Dist: marshmallow
Requires-Dist: ruamel.yaml
Requires-Dist: sox
Requires-Dist: unidecode
